flatland_railway_extension/FlatlandEnvironmentHelper.py
flatland_railway_extension/FlatlandGraphBuilder.py
flatland_railway_extension/RailroadSwitchAnalyser.py
flatland_railway_extension/RailroadSwitchCluster.py
flatland_railway_extension/__init__.py
flatland_railway_extension/environments/DynamicAgent.py
flatland_railway_extension/environments/DynamicsResourceData.py
flatland_railway_extension/environments/FlatlandDynamics.py
flatland_railway_extension/environments/FlatlandDynamicsDistanceMap.py
flatland_railway_extension/environments/FlatlandResourceAllocator.py
flatland_railway_extension/environments/InfrastructureData.py
flatland_railway_extension/environments/MultiResourcesAllocationAgent.py
flatland_railway_extension/environments/MultiResourcesAllocationRailEnv.py
flatland_railway_extension/environments/RollingStock.py
flatland_railway_extension/environments/__init__.py
flatland_railway_extension/examples/__init__.py
flatland_railway_extension/examples/demo_flatland_dynamics.py
flatland_railway_extension/examples/demo_flatland_extensions.py
flatland_railway_extension/examples/demo_flatland_graph.py
flatland_railway_extension/examples/demo_flatland_railroad_cluster.py
flatland_railway_extension/examples/demo_simple_flatland_navigation.py
flatland_railway_extension/examples/data_exports/FlatlandRecifeExporter.py
flatland_railway_extension/examples/data_exports/__init__.py
flatland_railway_extension/utils/FlatlandDynamicsRenderer.py
flatland_railway_extension/utils/FlatlandRenderer.py
flatland_railway_extension/utils/ShortestPathNextStepObservation.py
flatland_railway_extension/utils/__init__.py
flatland_railway_extension/utils/cached_methods.py
flatland_railway_extension-0.2.12.dist-info/LICENSE
flatland_railway_extension-0.2.12.dist-info/METADATA
flatland_railway_extension-0.2.12.dist-info/WHEEL
flatland_railway_extension-0.2.12.dist-info/top_level.txt
flatland_railway_extension-0.2.12.dist-info/RECORD
